{"id":0,"depth":0,"data":{"1":{"c1":null,"sum":{"pJum":356,"per":5,"pTSah":66,"error":143,"cakupan":5184,"pending":430,"psi":12,"ger":147,"ppp":54,"nas":92,"tSah":26337,"janggal":230,"jum":477839,"pSah":506,"pas2":763708,"sej":121,"sah":890509,"pan":93,"pas1":127350,"pdi":107,"han":18,"dem":127,"pkb":125,"gol":185,"ber":39,"pbb":10,"pkp":1,"gar":5},"ts":1556263084773},"6728":{"ts":1556263422188,"c1":null,"sum":{"pJum":1378,"per":44,"pTSah":86,"error":284,"cakupan":14699,"pending":1754,"psi":55,"ger":173,"ppp":19,"nas":174,"tSah":34782,"janggal":472,"jum":1534090,"pSah":735,"pas2":1196553,"sej":140,"sah":2355771,"pan":79,"pas1":1161071,"pdi":494,"han":14,"dem":44,"pkb":73,"gol":215,"ber":36,"pbb":1,"pkp":5,"gar":17}},"12920":{"sum":{"pdi":58,"han":5,"dem":67,"pkb":24,"gol":61,"ber":5,"pbb":33,"pkp":8,"gar":3,"pJum":347,"per":5,"pTSah":43,"error":112,"cakupan":8622,"pending":824,"psi":13,"ger":236,"ppp":48,"nas":109,"tSah":20127,"janggal":307,"jum":1134077,"pSah":559,"pas2":1173697,"sej":141,"sah":1342886,"pan":139,"pas1":170553},"ts":1556260935850,"c1":null},"14086":{"c1":null,"sum":{"pas2":703694,"sej":18,"sah":1052710,"pan":0,"pas1":350191,"han":1,"dem":42,"pkb":7,"ber":31,"pbb":4,"pkp":0,"gar":0,"pJum":804,"per":4,"pTSah":34,"error":149,"cakupan":8348,"pending":2823,"psi":1,"ger":0,"ppp":9,"nas":32,"tSah":14558,"janggal":360,"jum":696911,"pSah":259},"ts":1556263401157},"15885":{"c1":null,"sum":{"janggal":217,"jum":465303,"pSah":277,"pas2":367436,"sej":15,"sah":600596,"pan":65,"pas1":233590,"pdi":25,"han":3,"dem":16,"pkb":15,"gol":107,"ber":1,"pbb":3,"pkp":2,"gar":1,"pJum":643,"per":6,"pTSah":92,"error":76,"cakupan":4455,"pending":1239,"psi":4,"ger":84,"ppp":8,"nas":5,"tSah":13461},"ts":1556246625684},"17404":{"sum":{"pas1":559858,"han":11,"dem":79,"pdi":423,"pkb":266,"gol":154,"ber":21,"pbb":3,"pkp":0,"gar":1,"per":10,"pTSah":74,"error":99,"cakupan":9810,"pending":2294,"psi":47,"ger":225,"ppp":3,"nas":45,"tSah":33087,"janggal":438,"jum":1126726,"pSah":755,"pas2":950535,"sej":6,"sah":1507926,"pan":11},"ts":1556259115674,"c1":null},"20802":{"c1":null,"sum":{"pkb":93,"gol":242,"ber":17,"pbb":2,"pkp":4,"gar":1,"pJum":544,"per":13,"pTSah":199,"error":111,"cakupan":3534,"pending":3,"psi":7,"ger":237,"ppp":31,"nas":75,"tSah":16920,"janggal":209,"jum":586586,"pSah":953,"pas2":329769,"sej":124,"sah":654829,"pan":163,"pas1":326369,"pdi":314,"han":10,"dem":26},"ts":1556257811041},"22328":{"ts":1556263203309,"c1":null,"sum":{"pdi":482,"han":20,"dem":80,"pkb":292,"gol":240,"ber":60,"pbb":6,"pkp":1,"gar":30,"pJum":1099,"per":88,"pTSah":108,"error":204,"cakupan":8043,"pending":1067,"psi":51,"ger":365,"ppp":81,"nas":386,"tSah":23828,"janggal":339,"jum":1040744,"pSah":786,"pas2":608111,"sej":507,"sah":1306957,"pan":266,"pas1":699811}},"24993":{"sum":{"pas1":197042,"dem":31,"pdi":80,"han":2,"pkb":9,"gol":14,"pbb":10,"pkp":1,"pJum":253,"per":8,"pTSah":135,"error":62,"cakupan":1581,"pending":23,"psi":1,"ger":7,"ppp":3,"tSah":9799,"janggal":73,"jum":292853,"pSah":30,"pas2":120542,"sah":316800,"pan":1},"ts":1556255834189,"c1":null},"25405":{"ts":1556261794819,"c1":null,"sum":{"cakupan":3335,"pending":201,"psi":2,"ger":38,"ppp":5,"nas":50,"tSah":9140,"janggal":293,"jum":456181,"pSah":271,"pas2":282632,"sej":15,"sah":594736,"pan":19,"pas1":313862,"pdi":58,"han":7,"dem":92,"pkb":12,"gol":28,"ber":2,"pbb":1,"pkp":0,"gar":0,"pJum":306,"per":5,"pTSah":178,"error":0}},"25823":{"ts":1556263404739,"c1":null,"sum":{"pkb":506,"gol":613,"ber":147,"pbb":78,"pkp":31,"gar":31,"pJum":4373,"per":241,"pTSah":855,"error":792,"cakupan":17522,"pending":282,"psi":2176,"ger":1384,"ppp":202,"nas":557,"tSah":50111,"janggal":1162,"jum":1829067,"pSah":7833,"pas2":1803961,"sej":2153,"sah":3761246,"pan":747,"pas1":1959516,"pdi":4001,"han":68,"dem":454}},"26141":{"sum":{"sah":6508500,"pan":1373,"pas1":2638310,"pdi":3212,"han":62,"dem":807,"pkb":1601,"gol":2960,"ber":272,"pbb":76,"pkp":19,"gar":61,"pJum":7250,"per":288,"pTSah":964,"error":691,"cakupan":35294,"pending":2269,"psi":555,"ger":4807,"ppp":362,"nas":430,"tSah":138224,"janggal":869,"jum":2716720,"pSah":10034,"pas2":3874291,"sej":2755},"ts":1556263429651,"c1":null},"32676":{"c1":null,"sum":{"janggal":805,"jum":4838197,"pSah":4926,"pas2":1466615,"sej":748,"sah":6262208,"pan":395,"pas1":4798345,"pdi":3868,"han":21,"dem":559,"pkb":2188,"gol":1443,"ber":110,"pbb":19,"pkp":8,"gar":20,"pJum":7145,"per":134,"pTSah":601,"error":490,"cakupan":35466,"pending":2569,"psi":219,"ger":1363,"ppp":291,"nas":397,"tSah":176859},"ts":1556263419664},"41863":{"sum":{"pbb":117,"pkp":7,"gar":6,"pJum":967,"per":25,"pTSah":109,"error":163,"cakupan":6067,"pending":2,"psi":151,"ger":149,"ppp":59,"nas":185,"tSah":27772,"janggal":222,"jum":740805,"pSah":1511,"pas2":370653,"sej":231,"sah":1207274,"pan":346,"pas1":837940,"pdi":881,"han":13,"dem":73,"pkb":353,"gol":319,"ber":54},"ts":1556259966446,"c1":null},"42385":{"sum":{"pkb":1261,"gol":741,"ber":113,"pbb":110,"pkp":10,"gar":12,"pJum":7290,"per":113,"pTSah":1068,"error":390,"cakupan":28710,"pending":3479,"psi":359,"ger":549,"ppp":284,"nas":292,"tSah":151164,"janggal":498,"jum":2551061,"pSah":4699,"pas2":1594868,"sej":257,"sah":4788404,"pan":327,"pas1":3195951,"pdi":1645,"han":78,"dem":293},"ts":1556263426191,"c1":null},"51578":{"ts":1556263423787,"c1":null,"sum":{"pkb":336,"gol":697,"ber":60,"pbb":135,"pkp":4,"gar":14,"pJum":4800,"per":74,"pTSah":838,"error":228,"cakupan":12907,"pending":3494,"psi":532,"ger":784,"ppp":211,"nas":297,"tSah":54471,"janggal":519,"jum":1056108,"pSah":3575,"pas2":1198018,"sej":737,"sah":2008915,"pan":225,"pas1":814429,"pdi":1458,"han":36,"dem":315}},"53241":{"ts":1556260527780,"c1":null,"sum":{"pending":270,"psi":170,"ger":172,"ppp":29,"nas":527,"tSah":19580,"janggal":219,"jum":748599,"pSah":1303,"pas2":78318,"sej":438,"sah":958870,"pan":17,"pas1":880861,"pdi":1429,"dem":237,"han":142,"pkb":78,"gol":516,"ber":79,"pbb":6,"pkp":36,"gar":32,"pJum":1575,"per":74,"pTSah":150,"error":110,"cakupan":4864}},"54020":{"sum":{"error":222,"cakupan":4963,"pas1":163622,"pending":2057,"dem":21,"han":68,"tSah":15558,"janggal":109,"jum":382125,"pas2":388601,"pbb":21,"pkp":2,"sah":551553},"ts":1556262210879,"c1":null},"55065":{"c1":null,"sum":{"janggal":118,"jum":390612,"pkb":9,"gol":20,"ber":2,"pas2":58483,"sej":0,"gar":1,"sah":447684,"error":54,"cakupan":2948,"pas1":389912,"pending":436,"pdi":83,"ger":5,"nas":21,"tSah":7866},"ts":1556263431011},"58285":{"c1":null,"sum":{"pJum":2001,"per":80,"pTSah":282,"error":154,"cakupan":6732,"pending":724,"psi":29,"ger":151,"ppp":72,"nas":121,"tSah":20050,"janggal":515,"jum":954021,"pSah":1229,"pas2":557059,"sej":155,"sah":1103984,"pan":108,"pas1":549168,"pdi":453,"han":117,"dem":52,"pkb":225,"gol":202,"ber":29,"pbb":41,"pkp":0,"gar":3},"ts":1556263426968},"60371":{"c1":null,"sum":{"janggal":158,"jum":381334,"pkb":5,"gol":18,"ber":2,"pas2":201306,"sej":43,"sah":457576,"error":2,"cakupan":2970,"pas1":258457,"pending":246,"han":1,"psi":4,"pdi":34,"ppp":6,"tSah":11608},"ts":1556256357859},"61965":{"c1":null,"sum":{"pending":866,"psi":0,"ger":51,"ppp":10,"nas":17,"tSah":14910,"janggal":108,"jum":243550,"pSah":278,"pas2":299154,"sej":133,"sah":454118,"pan":48,"pas1":155158,"han":0,"dem":4,"pdi":12,"pkb":18,"gol":48,"ber":18,"pbb":12,"pkp":0,"gar":0,"per":5,"pTSah":31,"error":54,"cakupan":3291},"ts":1556263429128},"64111":{"sum":{"gar":0,"pJum":402,"per":20,"pTSah":113,"error":72,"cakupan":3947,"pending":1145,"psi":4,"ger":14,"ppp":98,"nas":66,"tSah":11214,"janggal":168,"jum":328612,"pSah":357,"pas2":262452,"sej":40,"sah":547858,"pan":11,"pas1":286761,"han":0,"pdi":34,"pkb":19,"gol":43,"ber":16},"ts":1556262163350,"c1":null},"65702":{"sum":{"pbb":1,"pkp":0,"gar":3,"per":56,"error":47,"cakupan":1698,"pending":3,"psi":3,"ger":8,"ppp":1,"nas":103,"tSah":3668,"janggal":117,"jum":260746,"pas2":91700,"sej":2,"sah":333213,"pan":2,"pas1":241805,"han":20,"dem":7,"pdi":268,"pkb":2,"gol":99,"ber":9},"ts":1556262631619,"c1":null},"67393":{"sum":{"janggal":96,"error":62,"cakupan":2005,"pas1":156372,"jum":204334,"pkb":34,"pending":282,"pas2":154690,"tSah":3626,"sah":310567},"ts":1556261313797,"c1":null},"69268":{"sum":{"pkb":434,"gol":307,"ber":49,"pbb":32,"pkp":2,"gar":14,"pJum":2558,"per":113,"pTSah":334,"error":85,"cakupan":7981,"pending":3024,"psi":48,"ger":431,"ppp":250,"nas":502,"tSah":18822,"janggal":146,"jum":547422,"pSah":1770,"pas2":574959,"sej":96,"sah":960802,"pan":180,"pas1":386959,"pdi":373,"han":26,"dem":199},"ts":1556260914810,"c1":null},"72551":{"c1":null,"sum":{"pkb":22,"gol":84,"ber":5,"pbb":41,"pkp":0,"gar":1,"pJum":142,"per":5,"pTSah":5,"error":77,"cakupan":2913,"pending":451,"psi":22,"ger":57,"ppp":4,"nas":86,"tSah":8766,"janggal":115,"jum":370044,"pSah":137,"pas2":266850,"sej":143,"sah":434010,"pan":27,"pas1":167900,"pdi":192,"dem":51,"han":13},"ts":1556256763278},"74716":{"c1":null,"sum":{"tSah":3621,"janggal":72,"jum":230587,"pkb":8,"pSah":247,"gol":134,"ber":0,"pas2":149044,"sej":17,"gar":0,"pan":3,"sah":298462,"per":1,"pTSah":18,"error":33,"cakupan":1654,"pas1":149578,"pending":244,"pdi":66,"psi":1,"ger":63,"ppp":4},"ts":1556258353256},"75425":{"ts":1556208492807,"c1":null,"sum":{"pending":69,"pas2":55446,"tSah":2331,"sah":147557,"janggal":41,"error":39,"cakupan":850,"pas1":92111,"jum":121114}},"76096":{"c1":null,"sum":{"ppp":0,"nas":31,"tSah":2833,"janggal":115,"jum":163957,"pSah":112,"ber":5,"pas2":99330,"sej":14,"gar":0,"pan":1,"sah":248301,"pJum":2260,"per":13,"pTSah":5,"error":54,"cakupan":1457,"pas1":149174,"pending":109,"psi":2},"ts":1556263298640},"77085":{"c1":null,"sum":{"janggal":55,"error":10,"cakupan":1106,"pas1":58908,"jum":84817,"pending":329,"pas2":80382,"tSah":1726,"sah":139587,"pJum":158},"ts":1556259042589},"78203":{"c1":null,"sum":{"janggal":47,"jum":39916,"pkb":49,"gol":25,"pas2":27189,"sah":94104,"error":52,"cakupan":511,"pas1":66913,"pending":0,"pdi":30,"ger":16,"tSah":2295},"ts":1556245786495},"81877":{"c1":null,"sum":{"pending":2,"pas2":18477,"tSah":587,"sah":62102,"pJum":69,"janggal":1,"error":0,"cakupan":372,"pas1":43625,"jum":16404},"ts":1556249908804},"928068":{"c1":null,"sum":{"nas":2,"tSah":3057,"janggal":71,"jum":126972,"pSah":369,"pas2":48458,"sej":16,"sah":144697,"pan":0,"pas1":97384,"pdi":7,"han":0,"dem":46,"pkb":8,"gol":1,"ber":0,"pbb":8,"pkp":0,"gar":1,"pJum":411,"per":2,"pTSah":34,"error":24,"cakupan":897,"pending":37,"psi":0,"ger":2,"ppp":4},"ts":1556253899639},"-99":{"c1":null,"sum":{"pdi":11810,"han":150,"dem":748,"pkb":2154,"gol":1715,"ber":355,"pbb":82,"pkp":82,"gar":70,"pJum":23979,"per":362,"pTSah":1311,"error":75,"cakupan":742,"pending":19,"psi":6988,"ger":1624,"ppp":597,"nas":1019,"tSah":6801,"janggal":110,"jum":98547,"pSah":27130,"pas2":73454,"sej":2676,"sah":285270,"pan":573,"pas1":211816},"ts":1556254277376}},"parentIds":[],"name":"IDN","parentNames":[],"children":[[1,"ACEH",17389,1734674,1789100],[6728,"SUMATERA UTARA",42668,4838923,4946830],[12920,"SUMATERA BARAT",16719,1836875,1881128],[14086,"RIAU",17642,1963184,1900013],[15885,"JAMBI",11342,1249398,1226257],[17404,"SUMATERA SELATAN",25332,2965679,2911896],[20802,"BENGKULU",6165,708242,690866],[22328,"LAMPUNG",28060,3101750,2972387],[24993,"KEPULAUAN BANGKA BELITUNG",3803,475784,456785],[25405,"KEPULAUAN RIAU",5478,619882,609542],[25823,"DKI JAKARTA",29063,3874021,3887577],[26141,"JAWA BARAT",138136,16724460,16546385],[32676,"JAWA TENGAH",115407,13901364,13995538],[41863,"DAERAH ISTIMEWA YOGYAKARTA",11781,1330110,1401764],[42385,"JAWA TIMUR",130184,15226058,15686936],[51578,"BANTEN",33471,4100146,4012331],[53241,"BALI",12386,1556427,1573861],[54020,"NUSA TENGGARA BARAT",15989,1800915,1866338],[55065,"NUSA TENGGARA TIMUR",14981,1660843,1730773],[58285,"KALIMANTAN BARAT",16500,1879884,1807275],[60371,"KALIMANTAN TENGAH",8133,903010,850214],[61965,"KALIMANTAN SELATAN",13153,1436959,1432207],[64111,"KALIMANTAN TIMUR",11334,1285070,1195671],[65702,"SULAWESI UTARA",7828,965308,942533],[67393,"SULAWESI TENGAH",9191,994173,958637],[69268,"SULAWESI SELATAN",26355,2987564,3171811],[72551,"SULAWESI TENGGARA",7817,860459,863080],[74716,"GORONTALO",3364,405117,407684],[75425,"SULAWESI BARAT",3865,433985,431259],[76096,"MALUKU",5524,622403,643631],[77085,"MALUKU UTARA",3805,405056,398927],[78203,"PAPUA",15272,1891502,1649515],[81877,"PAPUA BARAT",3915,385927,356318],[928068,"KALIMANTAN UTARA",2186,236229,213879],[-99,"LUAR NEGERI",3174,-1,-1]]}