{"id":12920,"name":"SUMATERA BARAT","depth":1,"parentIds":[0],"parentNames":["IDN"],"children":[[12921,"PESISIR SELATAN",1479,163386,167874],[13010,"SOLOK",1315,139896,142006],[13099,"SIJUNJUNG",717,77741,78620],[13163,"TANAH DATAR",1249,136146,140469],[13253,"PADANG PARIAMAN",1359,155446,158541],[13317,"AGAM",1624,180307,184722],[13416,"LIMA PULUH KOTA",1256,129250,135911],[13509,"PASAMAN",915,98979,100857],[13554,"KEPULAUAN MENTAWAI",337,32772,30331],[13608,"DHARMASRAYA",667,72338,71569],[13634,"SOLOK SELATAN",598,57207,56954],[13681,"PASAMAN BARAT",1206,123846,126877],[13712,"KOTA PADANG",2457,290588,301574],[13828,"KOTA SOLOK",207,23388,24030],[13844,"KOTA SAWAHLUNTO",201,22564,23214],[13886,"KOTA PADANG PANJANG",177,19043,19738],[13905,"KOTA BUKITTINGGI",349,40153,41294],[13933,"KOTA PAYAKUMBUH",341,43594,45255],[14010,"KOTA PARIAMAN",265,30231,31292]],"data":{"12921":{"sum":{"pending":108,"janggal":84,"cakupan":1445,"pas2":219359,"tSah":3546,"sah":254682,"pas1":35153,"error":0,"jum":256643,"pkb":13,"gol":20,"pdi":3,"ger":109,"ber":2,"sej":30,"gar":0,"nas":14,"laporKpu":2},"ts":1557374326923,"c1":null},"13010":{"sum":{"janggal":64,"cakupan":1265,"pending":103,"pas2":166790,"tSah":3412,"sah":183007,"pas1":16269,"error":0,"ger":56,"jum":188204,"psi":1,"ppp":9,"pan":27,"per":8,"ber":11,"sej":29,"gar":8,"nas":28,"pkb":6,"gol":87,"pdi":4,"pTSah":8,"pSah":156,"laporKpu":1},"ts":1557297586589,"c1":null},"13099":{"sum":{"janggal":32,"cakupan":714,"pending":13,"error":0,"tSah":1650,"sah":120631,"pas1":15007,"pas2":105590,"jum":123445,"laporKpu":0},"ts":1557241534179,"c1":null},"13163":{"sum":{"pending":56,"janggal":88,"cakupan":1098,"tSah":3363,"sah":170476,"pas1":19076,"pas2":152200,"jum":170495,"pJum":165,"error":0,"laporKpu":1},"ts":1557333908440,"c1":null},"13253":{"sum":{"janggal":83,"cakupan":1297,"pending":59,"tSah":4109,"sah":199253,"pas1":19117,"pas2":180317,"dem":7,"han":2,"pbb":27,"pkp":0,"jum":204173,"error":0,"ppp":6,"pan":9,"per":2,"psi":2,"nas":1,"ber":2,"sej":11,"gar":0,"laporKpu":0},"ts":1557346329663,"c1":null},"13317":{"sum":{"janggal":106,"cakupan":1600,"pending":57,"pas1":24546,"pas2":224211,"tSah":4184,"sah":248394,"error":0,"jum":252048,"laporKpu":1},"ts":1557346442381,"c1":null},"13416":{"sum":{"pending":57,"janggal":44,"cakupan":1227,"error":0,"tSah":3774,"sah":204529,"pas1":25013,"pas2":179909,"jum":199546,"pJum":182,"pkb":13,"ger":14,"pdi":3,"gol":4,"nas":4,"gar":1,"ber":0,"sej":39,"per":1,"ppp":3,"psi":3,"pan":70,"han":2,"dem":16,"laporKpu":0},"ts":1557283846670,"c1":null},"13509":{"sum":{"pending":17,"janggal":38,"cakupan":584,"tSah":1979,"sah":99944,"pas1":8096,"pas2":92206,"jum":101178,"pkb":4,"gol":24,"pdi":11,"ger":101,"psi":1,"ppp":9,"pan":22,"per":0,"han":0,"dem":28,"pbb":2,"pkp":0,"error":0,"laporKpu":0,"pTSah":18,"pSah":81},"ts":1557328540061,"c1":null},"13554":{"sum":{"pending":0,"janggal":20,"cakupan":236,"pas2":7248,"tSah":319,"sah":35002,"pas1":27743,"jum":35260,"error":0,"pkb":0,"gol":5,"pdi":16,"ger":16,"han":10,"dem":4,"pbb":2,"pkp":0,"laporKpu":0},"ts":1557290947917,"c1":null},"13608":{"sum":{"pending":15,"janggal":36,"cakupan":657,"pas2":86263,"tSah":1744,"sah":124209,"pas1":37908,"jum":125128,"error":0,"laporKpu":1},"ts":1557346381690,"c1":null},"13634":{"sum":{"janggal":35,"cakupan":564,"pending":19,"tSah":1594,"sah":86714,"pas1":13218,"pas2":73505,"error":0,"jum":87994,"laporKpu":0},"ts":1557227054469,"c1":null},"13681":{"sum":{"pending":16,"janggal":86,"cakupan":872,"pas2":132078,"tSah":2531,"sah":155314,"pas1":23614,"error":0,"jum":146433,"laporKpu":3},"ts":1557282605938,"c1":null},"13712":{"sum":{"janggal":144,"cakupan":2211,"pending":92,"jum":408732,"pas2":359804,"tSah":3847,"sah":416218,"pas1":57419,"error":0,"pTSah":15,"pSah":390,"pdi":21,"ber":0,"sej":81,"gar":1,"nas":70,"pan":14,"per":2,"psi":5,"ppp":11,"pbb":2,"pkb":0,"laporKpu":0},"ts":1557290821081,"c1":null},"13828":{"sum":{"pending":6,"janggal":11,"cakupan":202,"pas1":4253,"pas2":30864,"tSah":373,"sah":35117,"jum":36424,"pkb":8,"gol":39,"pdi":25,"ger":106,"error":0,"laporKpu":0},"ts":1557228408836,"c1":null},"13844":{"sum":{"janggal":8,"cakupan":200,"pending":9,"dem":16,"han":1,"psi":2,"ppp":19,"nas":34,"sej":9,"ger":35,"gol":8,"jum":38593,"pTSah":28,"pSah":169,"pkp":8,"pbb":2,"pkb":2,"pdi":3,"ber":3,"gar":1,"pan":24,"tSah":601,"sah":38304,"pas1":7039,"pas2":31265,"error":0,"laporKpu":0},"ts":1557277744071,"c1":null},"13886":{"sum":{"janggal":6,"cakupan":177,"pending":2,"pas2":27645,"tSah":342,"sah":31642,"pas1":3993,"jum":31782,"error":0,"laporKpu":0},"ts":1557066342135,"c1":null},"13905":{"sum":{"janggal":28,"cakupan":350,"pending":16,"tSah":848,"sah":62034,"pas1":7751,"pas2":54444,"jum":62580,"error":0,"laporKpu":0},"ts":1557236362322,"c1":null},"13933":{"sum":{"pending":37,"janggal":32,"cakupan":341,"pas2":63899,"tSah":1041,"sah":73425,"pas1":9472,"jum":74526,"error":0,"laporKpu":0},"ts":1557245029296,"c1":null},"14010":{"sum":{"janggal":11,"cakupan":254,"pending":15,"pas2":44537,"tSah":714,"sah":48443,"pas1":4006,"jum":48482,"error":0,"laporKpu":0},"ts":1557315105303,"c1":null}}}