{"id":14086,"name":"RIAU","depth":1,"parentIds":[0],"parentNames":["IDN"],"children":[[14087,"KEPULAUAN MERANTI",655,74084,69495],[14166,"KAMPAR",2229,241054,234381],[14414,"INDRAGIRI HULU",1205,146117,140886],[14630,"BENGKALIS",1800,197819,188122],[14741,"INDRAGIRI HILIR",1997,240042,225215],[14955,"PELALAWAN",942,106087,101089],[15087,"ROKAN HULU",1515,159427,155219],[15254,"ROKAN HILIR",1869,202936,194939],[15412,"SIAK",1244,140263,132872],[15553,"KUANTAN SINGINGI",897,113044,111854],[15775,"KOTA PEKANBARU",2448,250082,257131],[15846,"KOTA DUMAI",841,92229,88810]],"data":{"14087":{"sum":{"janggal":28,"cakupan":557,"pending":65,"jum":80103,"error":13,"pas2":44173,"tSah":1978,"sah":80217,"pas1":36386},"ts":1556328504462,"c1":null},"14166":{"sum":{"pending":96,"janggal":15,"cakupan":698,"pas1":24705,"pas2":81716,"tSah":1215,"sah":106370,"error":3,"jum":56547,"pJum":201,"pkb":7,"nas":24,"per":2,"dem":27,"pSah":259,"pTSah":34,"ger":0,"ber":15,"sej":0,"gar":0},"ts":1556325101488,"c1":null},"14414":{"sum":{"janggal":48,"cakupan":626,"pending":15,"pas1":46978,"pas2":71461,"tSah":2168,"sah":118285,"error":17,"jum":105450},"ts":1556284363125,"c1":null},"14630":{"sum":{"janggal":22,"cakupan":828,"pending":372,"tSah":1358,"sah":87211,"pas1":29170,"pas2":58037,"error":8,"jum":52266},"ts":1556289223936,"c1":null},"14741":{"sum":{"janggal":19,"cakupan":641,"pending":215,"tSah":2412,"sah":84179,"pas1":30882,"pas2":53363,"error":10,"jum":46245},"ts":1556324998984,"c1":null},"14955":{"sum":{"pending":256,"janggal":11,"cakupan":399,"pas2":17010,"tSah":322,"sah":27906,"pas1":10896,"jum":11047,"error":5},"ts":1556328577448,"c1":null},"15087":{"sum":{"pending":336,"janggal":20,"cakupan":745,"pas2":41684,"tSah":946,"sah":74221,"pas1":32536,"jum":64491,"error":5,"dem":15,"han":1,"pbb":1,"pkp":0,"ppp":9,"pan":0,"per":2,"psi":1},"ts":1556326616532,"c1":null},"15254":{"sum":{"pending":645,"janggal":21,"cakupan":928,"tSah":951,"sah":47435,"pas1":23686,"pas2":23848,"error":8,"jum":41845},"ts":1556328600342,"c1":null},"15412":{"sum":{"janggal":15,"cakupan":708,"pending":453,"tSah":618,"sah":52569,"pas1":18634,"pas2":33929,"error":9,"jum":40020},"ts":1556288448063,"c1":null},"15553":{"sum":{"janggal":4,"cakupan":159,"pending":0,"pas2":26665,"tSah":403,"sah":33785,"pas1":7119,"jum":8817,"error":1},"ts":1556194529546,"c1":null},"15775":{"sum":{"pending":28,"janggal":149,"cakupan":1648,"pas2":234738,"tSah":2647,"sah":315333,"pas1":81176,"error":51,"jum":185546,"pJum":603,"pbb":3,"gar":0,"nas":8,"ber":16,"sej":18},"ts":1556279171405,"c1":null},"15846":{"sum":{"janggal":37,"cakupan":616,"pending":1,"tSah":1395,"sah":114679,"pas1":46327,"pas2":68352,"jum":107081,"error":26},"ts":1556185848242,"c1":null}}}