{"id":20802,"name":"BENGKULU","depth":1,"parentIds":[0],"parentNames":["IDN"],"children":[[20803,"BENGKULU TENGAH",375,41708,40415],[20923,"BENGKULU SELATAN",556,58535,57242],[21093,"REJANG LEBONG",806,102245,101091],[21265,"BENGKULU UTARA",893,106930,103184],[21492,"KAUR",417,45893,43671],[21702,"SELUMA",664,70480,67213],[21885,"MUKOMUKO",567,64780,61469],[22052,"LEBONG",363,39268,37957],[22135,"KEPAHIANG",517,55678,52727],[22252,"KOTA BENGKULU",1007,122725,125897]],"data":{"20803":{"sum":{"janggal":20,"cakupan":340,"pending":0,"pas1":30844,"pas2":33618,"tSah":1801,"sah":64462,"jum":59623,"error":11},"ts":1556462850371,"c1":null},"20923":{"sum":{"janggal":39,"cakupan":535,"pending":0,"pas2":45968,"tSah":1577,"sah":96823,"pas1":50855,"jum":96389,"pJum":260,"pTSah":10,"pSah":250,"pkp":0,"pkb":5,"pdi":39,"nas":8,"gar":0,"ber":2,"sej":8,"per":5,"ppp":1,"psi":0,"pan":114,"dem":9,"han":2,"error":9},"ts":1556469742215,"c1":null},"21093":{"sum":{"pending":239,"janggal":29,"cakupan":681,"pas2":56762,"tSah":3548,"sah":98854,"pas1":43005,"error":12,"jum":90664,"pTSah":107,"pSah":77,"pkb":5,"gol":64,"pdi":9,"ger":36},"ts":1556456708928,"c1":null},"21265":{"sum":{"janggal":41,"cakupan":830,"pending":140,"pas1":81315,"pas2":53969,"tSah":2875,"sah":135115,"error":26,"jum":136790,"sej":70,"gar":1,"nas":59,"ber":14,"pkb":60,"gol":94,"pdi":218,"ger":106,"han":4,"dem":1,"pbb":0,"pkp":3,"pTSah":14,"pSah":153},"ts":1556460537703,"c1":null},"21492":{"sum":{"janggal":21,"cakupan":413,"pending":93,"tSah":951,"sah":64872,"pas1":33635,"pas2":31293,"jum":63767,"error":4},"ts":1556470047966,"c1":null},"21702":{"sum":{"pending":153,"janggal":38,"cakupan":624,"tSah":2471,"sah":86045,"pas1":39274,"pas2":46923,"jum":87284,"error":10,"pJum":65},"ts":1556470078432,"c1":null},"21885":{"sum":{"pending":39,"janggal":30,"cakupan":464,"pas2":38794,"tSah":1680,"sah":78770,"pas1":39969,"jum":76131,"error":6,"ger":40,"psi":0,"ppp":1,"pan":2,"per":5,"pkb":27,"gol":18,"pdi":63,"pJum":231,"ber":1,"sej":3,"gar":1,"nas":30},"ts":1556461650572,"c1":null},"22052":{"sum":{"pending":1,"janggal":14,"cakupan":341,"tSah":2945,"sah":60147,"pas1":33353,"pas2":27155,"error":9,"jum":63160},"ts":1556459452267,"c1":null},"22135":{"sum":{"pending":142,"janggal":28,"cakupan":460,"pas2":29391,"tSah":1877,"sah":54093,"pas1":24675,"jum":53365,"error":5,"pdi":29,"ger":21,"pkb":3,"gol":23,"pTSah":19,"pSah":84},"ts":1556465599667,"c1":null},"22252":{"sum":{"janggal":79,"cakupan":824,"pending":152,"tSah":1841,"sah":140061,"pas1":59569,"pas2":80589,"jum":127503,"error":42,"han":4,"dem":16,"pbb":2,"pkp":1,"psi":7,"ppp":30,"pan":49,"per":8,"pSah":389,"pTSah":49,"pdi":30,"ger":64,"pkb":25,"gol":76,"ber":3,"sej":69,"gar":0,"nas":20,"pJum":219},"ts":1556469660035,"c1":null}}}