{"id":22328,"name":"LAMPUNG","depth":1,"parentIds":[0],"parentNames":["IDN"],"children":[[22329,"PRINGSEWU",1416,152151,143783],[22439,"MESUJI",601,79759,73915],[22522,"TULANG BAWANG BARAT",797,100613,95862],[22605,"LAMPUNG SELATAN",3096,386604,372591],[22875,"LAMPUNG TENGAH",3954,484806,465760],[23189,"LAMPUNG UTARA",3874,223934,217117],[23460,"LAMPUNG BARAT",966,110946,100847],[23737,"TULANG BAWANG",1216,149041,138074],[23903,"TANGGAMUS",1975,233391,220851],[24202,"LAMPUNG TIMUR",3440,401540,388609],[24484,"WAY KANAN",1518,173477,165983],[24709,"KOTA BANDAR LAMPUNG",2777,320595,317579],[24822,"KOTA METRO",465,56728,57583],[24850,"PESAWARAN",1481,169316,160339],[928071,"PESISIR BARAT",484,58849,53494]],"data":{"22329":{"sum":{"pending":1,"janggal":16,"cakupan":710,"jum":117207,"pas2":45436,"tSah":2351,"sah":120681,"pas1":75348,"error":12},"ts":1556710188753,"c1":null},"22439":{"sum":{"janggal":33,"cakupan":477,"pending":0,"pas2":26253,"tSah":1622,"sah":94279,"pas1":68031,"jum":91109,"error":5,"pJum":212,"pdi":35,"ger":8,"pkb":17,"gol":28,"ber":1,"sej":12,"gar":0,"nas":21,"ppp":3,"pan":1,"per":9,"psi":23,"han":18,"dem":7,"pbb":2,"pkp":0},"ts":1556631812231,"c1":null},"22522":{"sum":{"pending":0,"janggal":30,"cakupan":692,"pas2":51242,"tSah":2771,"sah":139470,"pas1":88606,"error":13,"jum":143673,"sej":136,"pkb":57,"gol":169,"pdi":195,"ger":103,"pkp":0,"dem":34,"han":3,"pbb":0,"pTSah":14,"pSah":237,"ber":13,"gar":2,"nas":25,"pJum":218},"ts":1556632639988,"c1":null},"22605":{"sum":{"janggal":28,"cakupan":2633,"pending":0,"pas2":161257,"tSah":10623,"sah":465595,"pas1":304338,"jum":481063,"error":34,"pkb":39,"gol":54,"pdi":111,"ger":21,"ber":9,"sej":32,"gar":0,"nas":5,"per":2,"psi":2,"ppp":2,"pan":62},"ts":1556713268914,"c1":null},"22875":{"sum":{"pending":0,"janggal":124,"cakupan":3246,"error":18,"pas2":192735,"tSah":10864,"sah":579691,"pas1":387977,"jum":588815,"pkb":11},"ts":1556714877904,"c1":null},"23189":{"sum":{"janggal":69,"cakupan":1438,"pending":35,"pas2":128753,"tSah":4064,"sah":230871,"pas1":102337,"jum":218131,"error":202,"per":15,"nas":123,"pkb":44,"pan":36,"psi":6,"ppp":17,"dem":19,"han":1,"pbb":1,"pkp":1,"sej":67,"gar":4,"ber":18,"pdi":57,"ger":40,"gol":34},"ts":1556727058899,"c1":null},"23460":{"sum":{"pending":0,"janggal":44,"cakupan":918,"tSah":2977,"sah":168152,"pas1":95775,"pas2":72217,"jum":165699,"error":8,"pan":1,"per":5,"psi":2,"ppp":1,"han":0,"dem":1,"pbb":1,"pkp":0,"pkb":6,"gol":12,"pdi":90,"ger":28,"pJum":202},"ts":1556620808988,"c1":null},"23737":{"sum":{"janggal":75,"cakupan":1111,"pending":0,"pas1":136636,"pas2":65336,"tSah":3586,"sah":201972,"jum":204836,"han":0,"error":9,"psi":2,"ppp":2,"pan":7,"per":8,"ber":4,"sej":3,"gar":1,"nas":6},"ts":1556723256046,"c1":null},"23903":{"sum":{"janggal":22,"cakupan":840,"pending":121,"pas2":72210,"tSah":2317,"sah":128025,"pas1":55900,"jum":106332,"error":9,"pTSah":39,"pSah":349,"dem":3,"han":1,"pbb":1,"pkp":0},"ts":1556721285478,"c1":null},"24202":{"sum":{"janggal":20,"cakupan":1498,"pending":362,"pas2":54019,"tSah":2500,"sah":181463,"pas1":127553,"jum":161599,"error":12,"ppp":40,"pan":94,"per":33,"psi":17,"pTSah":71,"pSah":597,"pdi":91,"ger":94,"pkb":159,"gol":143,"ber":31,"sej":163,"gar":10,"nas":125,"han":1,"dem":87,"pbb":3,"pkp":0,"pJum":595},"ts":1556722429887,"c1":null},"24484":{"sum":{"pending":309,"janggal":25,"cakupan":1254,"pas1":87099,"pas2":75908,"tSah":3955,"sah":162078,"jum":166637,"error":10,"psi":1,"ppp":5,"pan":9,"per":0,"sej":13,"gar":4,"nas":9,"ber":0,"pdi":6,"ger":32,"pkb":109,"gol":17},"ts":1556702777064,"c1":null},"24709":{"sum":{"janggal":270,"cakupan":2252,"pending":89,"pas2":230642,"tSah":7319,"sah":425074,"pas1":194833,"error":138,"jum":388363,"pkb":95,"gol":125,"pdi":302,"ger":267,"pJum":1539,"sej":255,"gar":21,"nas":136,"ber":40,"pan":105,"per":11,"psi":5,"ppp":10,"pTSah":8,"pSah":107},"ts":1556718086512,"c1":null},"24822":{"sum":{"pending":1,"janggal":34,"cakupan":359,"tSah":1351,"sah":75000,"pas1":38558,"pas2":36417,"error":4,"jum":69543},"ts":1556724043981,"c1":null},"24850":{"sum":{"pending":372,"janggal":15,"cakupan":846,"pas2":40383,"tSah":1635,"sah":87810,"pas1":47476,"jum":85907,"error":10,"ber":5,"sej":48,"gar":0,"nas":66,"pkb":19,"gol":45,"pdi":59,"ger":50,"pan":15,"per":7,"psi":0,"ppp":6,"pJum":262},"ts":1556700837022,"c1":null},"928071":{"sum":{"janggal":45,"cakupan":428,"pending":0,"tSah":1495,"sah":79066,"pas1":40817,"pas2":38257,"jum":84791,"error":22},"ts":1556634951351,"c1":null}}}