{"depth":1,"data":{"25824":{"sum":{"pkb":5,"ber":1,"pbb":0,"gar":1,"pJum":246,"per":7,"pTSah":35,"error":0,"cakupan":76,"pending":0,"psi":2,"ger":9,"ppp":26,"nas":15,"tSah":368,"janggal":6,"jum":12792,"pSah":211,"pas2":7612,"sej":3,"sah":15903,"pan":46,"pas1":8291,"han":10,"dem":18,"pdi":7},"ts":1556876041883,"c1":null},"25833":{"ts":1557005344823,"c1":null,"sum":{"ber":10,"pbb":4,"pkp":1,"gar":4,"per":7,"pTSah":20,"error":0,"cakupan":2259,"pending":0,"psi":241,"ger":109,"ppp":10,"nas":31,"tSah":6935,"janggal":146,"jum":350267,"pSah":403,"pas2":235952,"sej":115,"sah":486541,"pan":29,"pas1":250834,"han":1,"dem":15,"pdi":472,"pkb":12,"gol":62}},"25886":{"c1":null,"sum":{"pkb":20,"gol":11,"ber":3,"pbb":2,"pkp":0,"gar":0,"pJum":982,"per":4,"pTSah":269,"error":0,"cakupan":3278,"pending":0,"psi":586,"ger":55,"ppp":2,"nas":32,"tSah":10226,"janggal":294,"jum":515686,"pSah":815,"pas2":288460,"sej":29,"sah":696892,"pan":15,"pas1":409511,"pdi":616,"han":2,"dem":13},"ts":1557005272500},"25924":{"ts":1556979938113,"c1":null,"sum":{"pas2":480045,"sej":207,"sah":1140649,"pan":127,"pas1":662597,"pdi":1057,"dem":123,"han":3,"pkb":64,"gol":51,"ber":20,"pbb":14,"pkp":3,"gar":3,"pJum":1279,"per":35,"pTSah":34,"error":0,"cakupan":5466,"pending":0,"psi":669,"ger":238,"ppp":23,"nas":117,"tSah":16334,"janggal":540,"jum":1027067,"pSah":615}},"25989":{"c1":null,"sum":{"pdi":1016,"dem":204,"han":22,"pkb":143,"gol":170,"ber":50,"pbb":41,"pkp":20,"gar":13,"pJum":1593,"per":132,"pTSah":258,"error":0,"cakupan":4603,"pending":1,"psi":571,"ger":495,"ppp":104,"nas":222,"tSah":13446,"janggal":287,"jum":612838,"pSah":3278,"pas2":508640,"sej":897,"sah":985063,"pan":176,"pas1":478151},"ts":1557005024296},"26065":{"c1":null,"sum":{"pdi":1072,"dem":87,"han":33,"pkb":274,"gol":344,"ber":74,"pbb":20,"pkp":7,"gar":8,"pJum":1762,"per":57,"pTSah":258,"error":0,"cakupan":5968,"pending":0,"psi":289,"ger":482,"ppp":40,"nas":143,"tSah":17596,"janggal":435,"jum":860242,"pSah":2878,"pas2":694623,"sej":988,"sah":1288953,"pan":370,"pas1":595261},"ts":1557004990194}},"parentIds":[0],"name":"DKI JAKARTA","parentNames":["IDN"],"id":25823,"children":[[25824,"KEPULAUAN SERIBU",81,9553,9460],[25833,"JAKARTA PUSAT",3002,404438,405537],[25886,"JAKARTA UTARA",4563,628487,625266],[25924,"JAKARTA BARAT",6730,874776,863486],[25989,"JAKARTA SELATAN",6453,842277,852039],[26065,"JAKARTA TIMUR",8234,1114490,1131789]]}