{"depth":1,"data":{"32677":{"sum":{"pending":196,"psi":0,"ger":22,"ppp":1,"nas":1,"tSah":12297,"janggal":47,"jum":744401,"pSah":294,"pas2":208668,"sej":0,"sah":759150,"pan":4,"pas1":550513,"han":1,"dem":18,"pdi":38,"laporKpu":6,"pkb":4,"gol":28,"ber":2,"pbb":0,"pkp":0,"gar":0,"per":1,"pTSah":9,"error":0,"cakupan":4361},"ts":1557451714018,"c1":null},"32986":{"c1":null,"sum":{"pkb":83,"gol":77,"ber":8,"pbb":1,"pkp":2,"gar":0,"pJum":420,"per":15,"pTSah":34,"error":0,"cakupan":4079,"pending":134,"psi":71,"ger":128,"ppp":3,"nas":33,"tSah":15109,"janggal":70,"jum":783036,"pSah":445,"pas2":204647,"sej":83,"sah":790547,"pan":13,"pas1":586343,"pdi":257,"han":0,"dem":59,"laporKpu":16},"ts":1557453649691},"33345":{"c1":null,"sum":{"janggal":58,"jum":521672,"pSah":205,"pas2":136451,"sej":63,"sah":512872,"pan":2,"pas1":376721,"pdi":92,"laporKpu":0,"pkb":30,"gol":30,"ber":3,"gar":1,"pJum":213,"per":5,"pTSah":31,"error":0,"cakupan":2616,"pending":100,"psi":0,"ger":28,"ppp":2,"nas":10,"tSah":17865},"ts":1557453761965},"33603":{"c1":null,"sum":{"janggal":70,"jum":587342,"pkb":89,"gol":12,"ber":0,"pas2":166755,"sej":12,"gar":0,"pan":5,"sah":567538,"pJum":191,"per":9,"error":0,"cakupan":3140,"pas1":400844,"pending":99,"pdi":17,"psi":7,"ger":17,"ppp":6,"nas":7,"tSah":20353,"laporKpu":0},"ts":1557423156519},"33902":{"c1":null,"sum":{"pas2":184022,"sej":31,"sah":666335,"pan":17,"pas1":482829,"pdi":90,"laporKpu":0,"pkb":127,"gol":100,"ber":5,"gar":2,"pJum":316,"per":8,"pTSah":15,"error":0,"cakupan":4182,"pending":211,"psi":2,"ger":78,"ppp":55,"nas":13,"tSah":20870,"janggal":63,"jum":697399,"pSah":162},"ts":1557453656481},"34389":{"c1":null,"sum":{"error":0,"cakupan":3007,"pending":128,"psi":1,"ger":47,"ppp":13,"nas":44,"tSah":13545,"janggal":76,"jum":466309,"pSah":415,"pas2":117964,"sej":26,"sah":450734,"pan":2,"pas1":333236,"pdi":251,"han":3,"dem":60,"laporKpu":0,"pkb":160,"gol":112,"ber":10,"pbb":2,"pkp":0,"gar":1,"pJum":523,"per":1,"pTSah":51},"ts":1557334708745},"34900":{"sum":{"pJum":426,"per":3,"pTSah":39,"error":0,"cakupan":2647,"pending":136,"psi":0,"ger":35,"ppp":34,"nas":4,"tSah":21322,"janggal":66,"jum":483714,"pSah":95,"pas2":96007,"sej":5,"sah":461674,"pan":14,"pas1":366089,"pdi":168,"dem":1,"han":0,"laporKpu":0,"pkb":98,"gol":96,"ber":2,"pbb":0,"pkp":0,"gar":1},"ts":1557457672462,"c1":null},"35181":{"c1":null,"sum":{"tSah":24190,"janggal":136,"jum":726479,"pSah":214,"pas2":199201,"sej":39,"sah":722373,"pan":3,"pas1":523656,"han":0,"dem":5,"laporKpu":1,"pkb":22,"ber":7,"pbb":1,"pkp":0,"gar":0,"pJum":213,"per":3,"pTSah":32,"error":0,"cakupan":3907,"pending":216,"psi":0,"ppp":37,"nas":22},"ts":1557452945961},"35575":{"ts":1557458303147,"c1":null,"sum":{"pas1":469568,"han":5,"dem":307,"pdi":4927,"laporKpu":0,"pkb":1451,"gol":1493,"ber":284,"pbb":19,"pkp":5,"gar":16,"per":299,"pTSah":49,"error":0,"cakupan":2589,"pending":72,"psi":49,"ger":879,"ppp":112,"nas":471,"tSah":12136,"janggal":26,"jum":538801,"pSah":441,"pas2":73393,"sej":316,"sah":542961,"pan":115}},"35862":{"ts":1557441067732,"c1":null,"sum":{"pkb":63,"gol":6,"ber":3,"pbb":1,"pkp":0,"gar":0,"pJum":370,"per":5,"pTSah":19,"error":0,"cakupan":4061,"pending":298,"psi":5,"ger":2,"ppp":7,"nas":63,"tSah":13616,"janggal":149,"jum":734468,"pSah":186,"pas2":149071,"sej":96,"sah":734188,"pan":48,"pas1":585750,"pdi":149,"han":0,"dem":6,"laporKpu":0}},"36290":{"sum":{"pending":116,"psi":14,"ger":101,"ppp":16,"nas":12,"tSah":11072,"janggal":112,"jum":544801,"pas2":124500,"sej":20,"sah":538108,"pan":74,"pas1":414140,"han":0,"dem":3,"pdi":99,"laporKpu":0,"pkb":25,"gol":15,"ber":2,"pbb":6,"pkp":0,"gar":0,"per":39,"error":0,"cakupan":2366},"ts":1557425481664,"c1":null},"36470":{"sum":{"sah":482683,"pan":0,"pas1":406969,"han":0,"dem":1,"pdi":55,"laporKpu":0,"pkb":5,"gol":12,"ber":4,"pbb":0,"pkp":0,"gar":0,"per":0,"error":0,"cakupan":3071,"pending":191,"psi":1,"ger":11,"ppp":0,"nas":2,"tSah":10411,"janggal":90,"jum":485926,"pas2":76219,"sej":37},"ts":1557439662028,"c1":null},"36790":{"c1":null,"sum":{"janggal":106,"jum":535416,"pSah":300,"pas2":106384,"sej":27,"sah":536032,"pan":47,"pas1":430012,"han":0,"dem":7,"pdi":211,"laporKpu":0,"pkb":5,"gol":35,"ber":2,"pbb":1,"pkp":0,"gar":1,"per":6,"pTSah":80,"error":0,"cakupan":3046,"pending":202,"psi":25,"ger":8,"ppp":1,"nas":3,"tSah":10264},"ts":1557418316211},"36985":{"sum":{"pending":144,"pdi":237,"ger":36,"nas":29,"tSah":13573,"laporKpu":0,"janggal":40,"jum":437459,"pkb":34,"pSah":178,"gol":240,"ber":0,"pas2":85688,"sej":13,"gar":0,"sah":450657,"pJum":144,"pTSah":6,"error":0,"cakupan":2604,"pas1":365381},"ts":1557455536328,"c1":null},"37214":{"c1":null,"sum":{"ber":112,"pbb":2,"pkp":2,"gar":12,"pJum":2348,"per":42,"pTSah":249,"error":0,"cakupan":3660,"pending":173,"psi":71,"ger":337,"ppp":119,"nas":214,"tSah":16579,"janggal":84,"jum":662302,"pSah":1510,"pas2":94780,"sej":182,"sah":648695,"pan":32,"pas1":554244,"pdi":1276,"han":30,"dem":44,"laporKpu":0,"pkb":482,"gol":148},"ts":1557447791501},"37514":{"ts":1557422123230,"c1":null,"sum":{"pkb":178,"gol":88,"ber":14,"pbb":0,"pkp":0,"gar":5,"pJum":1788,"per":5,"pTSah":47,"error":0,"cakupan":2818,"pending":100,"psi":5,"ger":117,"ppp":15,"nas":131,"tSah":19774,"janggal":57,"jum":537462,"pSah":163,"pas2":97646,"sej":37,"sah":513930,"pan":12,"pas1":416979,"pdi":315,"han":5,"dem":58,"laporKpu":0}},"37826":{"ts":1557423236232,"c1":null,"sum":{"per":2,"janggal":55,"error":0,"cakupan":1679,"pas1":235374,"jum":309613,"pending":118,"pas2":65349,"tSah":17779,"sah":300008,"laporKpu":0}},"38136":{"ts":1557452785639,"c1":null,"sum":{"pSah":204,"pas2":93894,"sej":33,"sah":674998,"pan":0,"pas1":581631,"pdi":724,"han":7,"dem":53,"laporKpu":0,"pkb":682,"gol":362,"ber":10,"pbb":1,"pkp":2,"gar":2,"pJum":1016,"per":2,"pTSah":8,"error":0,"cakupan":3949,"pending":325,"psi":0,"ger":254,"ppp":29,"nas":41,"tSah":22343,"janggal":91,"jum":699416}},"38564":{"ts":1557323292792,"c1":null,"sum":{"error":0,"cakupan":3032,"pas1":393119,"pending":95,"pdi":435,"psi":20,"ger":91,"ppp":11,"nas":380,"tSah":16751,"laporKpu":0,"janggal":98,"jum":533402,"pkb":128,"gol":271,"ber":27,"pas2":119376,"sej":50,"gar":6,"pan":44,"sah":512011,"pJum":1463,"per":12}},"38706":{"c1":null,"sum":{"sah":670324,"pan":3,"pas1":563132,"pdi":174,"han":0,"dem":6,"laporKpu":0,"pkb":14,"gol":9,"ber":3,"pbb":2,"pkp":1,"gar":1,"pJum":687,"per":3,"pTSah":18,"error":0,"cakupan":3186,"pending":140,"psi":5,"ger":15,"ppp":15,"nas":52,"tSah":24535,"janggal":116,"jum":687878,"pSah":211,"pas2":108888,"sej":8},"ts":1557422730382},"38917":{"c1":null,"sum":{"ppp":25,"nas":47,"tSah":21781,"janggal":49,"jum":621814,"pSah":188,"pas2":136866,"sej":47,"sah":602873,"pan":1,"pas1":466154,"pdi":449,"han":0,"dem":23,"laporKpu":0,"pkb":267,"gol":165,"ber":5,"pbb":1,"pkp":1,"gar":0,"pJum":393,"per":7,"pTSah":32,"error":0,"cakupan":3158,"pending":115,"psi":4,"ger":230},"ts":1557427354794},"39181":{"c1":null,"sum":{"pending":30,"psi":1,"ppp":28,"nas":30,"tSah":17719,"laporKpu":8,"janggal":109,"jum":622903,"pSah":180,"ber":2,"pas2":114321,"sej":45,"gar":0,"pan":3,"sah":613568,"pJum":1407,"per":1,"pTSah":14,"error":0,"cakupan":3020,"pas1":500678},"ts":1557403099321},"39436":{"sum":{"pending":135,"pdi":129,"ger":62,"nas":30,"tSah":15015,"laporKpu":0,"janggal":45,"jum":516882,"pkb":106,"gol":93,"ber":2,"pas2":99933,"sej":8,"gar":1,"sah":503392,"pJum":214,"error":0,"cakupan":2470,"pas1":403960},"ts":1557437619057,"c1":null},"39746":{"c1":null,"sum":{"janggal":47,"jum":579533,"pkb":33,"pSah":104,"gol":13,"pas2":121238,"pbb":0,"pkp":1,"sah":566167,"pJum":493,"pTSah":18,"error":0,"cakupan":3252,"pas1":445107,"pending":222,"pdi":93,"han":0,"dem":10,"ger":40,"tSah":20683,"laporKpu":0},"ts":1557375023539},"40053":{"c1":null,"sum":{"pdi":117,"ger":31,"nas":2,"tSah":18900,"laporKpu":0,"janggal":64,"jum":485798,"pkb":54,"gol":158,"ber":3,"pas2":90408,"sej":5,"gar":0,"sah":478372,"pJum":397,"error":0,"cakupan":2504,"pas1":388757,"pending":66},"ts":1557420519195},"40317":{"ts":1557440757330,"c1":null,"sum":{"han":0,"dem":18,"pdi":166,"laporKpu":0,"pkb":361,"gol":110,"ber":12,"pbb":0,"pkp":0,"gar":1,"per":14,"pTSah":53,"error":0,"cakupan":2869,"pending":131,"psi":4,"ger":84,"ppp":33,"nas":147,"tSah":17696,"janggal":98,"jum":559379,"pSah":575,"pas2":108487,"sej":17,"sah":542415,"pan":46,"pas1":434426}},"40622":{"c1":null,"sum":{"pending":138,"psi":2,"ger":68,"ppp":9,"nas":7,"tSah":11703,"janggal":15,"jum":422090,"pSah":331,"pas2":100525,"sej":21,"sah":411504,"pan":3,"pas1":310979,"han":0,"dem":5,"pdi":181,"laporKpu":0,"pkb":281,"gol":140,"ber":4,"pbb":0,"gar":0,"per":2,"pTSah":61,"error":0,"cakupan":2645},"ts":1557423880240},"40859":{"c1":null,"sum":{"janggal":172,"jum":838669,"pSah":364,"pas2":297143,"sej":137,"sah":806316,"pan":11,"pas1":512574,"pdi":334,"han":0,"dem":60,"laporKpu":1,"pkb":227,"gol":32,"ber":15,"pbb":1,"pkp":0,"gar":2,"pJum":245,"per":19,"pTSah":50,"error":0,"cakupan":4321,"pending":179,"psi":3,"ger":156,"ppp":14,"nas":30,"tSah":25279},"ts":1557447721883},"41165":{"sum":{"pending":162,"psi":0,"ger":156,"ppp":3,"nas":1,"tSah":18299,"janggal":85,"jum":674403,"pSah":288,"pas2":210121,"sej":19,"sah":689363,"pan":133,"pas1":480062,"pdi":134,"dem":0,"han":0,"laporKpu":0,"pkb":48,"gol":29,"ber":2,"pbb":0,"pkp":0,"gar":0,"pJum":488,"per":2,"pTSah":57,"error":0,"cakupan":4118},"ts":1557453225375,"c1":null},"41480":{"ts":1557339205486,"c1":null,"sum":{"ber":2,"pas2":19479,"sej":22,"gar":0,"sah":62426,"pJum":1114,"pTSah":21,"error":0,"cakupan":377,"pas1":42947,"pending":75,"pdi":427,"ger":74,"nas":15,"tSah":1619,"laporKpu":0,"janggal":18,"jum":60328,"pkb":68,"pSah":211,"gol":52}},"41501":{"c1":null,"sum":{"nas":3,"tSah":5066,"janggal":107,"jum":322607,"pSah":137,"pas2":57039,"sej":6,"sah":323742,"pan":0,"pas1":267086,"han":0,"dem":0,"pdi":274,"laporKpu":0,"pkb":7,"gol":5,"ber":1,"pbb":0,"pkp":0,"gar":0,"pJum":225,"per":3,"pTSah":12,"error":0,"cakupan":1547,"pending":6,"psi":16,"ger":12},"ts":1557452257932},"41558":{"c1":null,"sum":{"pending":0,"pas2":26148,"tSah":2621,"sah":118866,"laporKpu":0,"janggal":31,"error":0,"cakupan":610,"pas1":92678,"jum":120541},"ts":1557378718021},"41585":{"sum":{"ber":15,"pbb":5,"pkp":2,"gar":5,"pJum":1183,"per":23,"pTSah":29,"error":0,"cakupan":3433,"pending":124,"psi":56,"ger":257,"ppp":39,"nas":39,"tSah":15415,"janggal":218,"jum":712889,"pSah":217,"pas2":166808,"sej":108,"sah":741670,"pan":22,"pas1":577642,"pdi":560,"dem":224,"han":10,"laporKpu":0,"pkb":169,"gol":100},"ts":1557458705728,"c1":null},"41779":{"ts":1557455538518,"c1":null,"sum":{"nas":10,"tSah":4740,"laporKpu":0,"janggal":12,"jum":156045,"pkb":111,"ber":2,"pas2":39578,"sej":13,"gar":0,"sah":151985,"error":0,"cakupan":716,"pas1":112407,"pending":9}},"41831":{"c1":null,"sum":{"sah":155355,"pJum":224,"error":0,"cakupan":752,"pas1":96749,"pending":0,"pdi":72,"ger":30,"tSah":4107,"laporKpu":8,"janggal":37,"jum":158943,"pkb":10,"gol":21,"pas2":58797},"ts":1557403530931}},"parentIds":[0],"name":"JAWA TENGAH","parentNames":["IDN"],"id":32676,"children":[[32677,"CILACAP",5869,746142,742354],[32986,"BANYUMAS",5437,674636,676345],[33345,"PURBALINGGA",2898,378042,374169],[33603,"BANJARNEGARA",3167,396370,387800],[33902,"KEBUMEN",4538,541468,531240],[34389,"PURWOREJO",3032,305167,309444],[34900,"WONOSOBO",2935,345081,334017],[35181,"MAGELANG",4331,492312,496567],[35575,"BOYOLALI",3189,401136,407333],[35862,"KLATEN",4313,494152,510374],[36290,"SUKOHARJO",2402,331578,337968],[36470,"WONOGIRI",3913,430476,439348],[36790,"KARANGANYAR",3149,343587,351440],[36985,"SRAGEN",3360,383736,393164],[37214,"GROBOGAN",4629,557711,564558],[37514,"BLORA",2950,348985,357955],[37826,"REMBANG",2171,242801,245241],[38136,"PATI",4369,508799,525992],[38564,"KUDUS",3049,310632,319986],[38706,"JEPARA",3285,437542,438948],[38917,"DEMAK",3615,438861,438482],[39181,"SEMARANG",3182,383734,395259],[39436,"TEMANGGUNG",2475,299699,302610],[39746,"KENDAL",3445,389474,389156],[40053,"BATANG",2522,302837,303453],[40317,"PEKALONGAN",2879,366461,359329],[40622,"PEMALANG",4681,566973,555885],[40859,"TEGAL",4533,611049,595131],[41165,"BREBES",6180,772345,756304],[41480,"KOTA MAGELANG",407,43757,47574],[41501,"KOTA SURAKARTA",1734,205037,216962],[41558,"KOTA SALATIGA",614,65482,69667],[41585,"KOTA SEMARANG",4548,570520,605554],[41779,"KOTA PEKALONGAN",854,112837,113022],[41831,"KOTA TEGAL",752,101945,102907]]}