{"depth":1,"data":{"42386":{"ts":1556213256583,"c1":null,"sum":{"janggal":6,"jum":74967,"pkb":0,"gol":122,"ber":2,"pas2":59936,"sej":1,"pbb":30,"pkp":0,"gar":0,"sah":92018,"error":6,"cakupan":530,"pas1":32290,"pending":0,"han":0,"pdi":7,"dem":0,"ger":6,"nas":0,"tSah":2931}},"42570":{"ts":1556229164593,"c1":null,"sum":{"pending":1,"pas2":90462,"tSah":11394,"sah":321401,"janggal":31,"error":14,"cakupan":1616,"pas1":231243,"jum":214257}},"42897":{"c1":null,"sum":{"tSah":2070,"janggal":4,"jum":37849,"pkb":75,"gol":25,"pas2":16145,"pan":2,"sah":71044,"pJum":185,"error":1,"cakupan":434,"pas1":54899,"pending":42,"han":0,"pdi":42,"ger":13,"ppp":1},"ts":1556188690475},"43069":{"ts":1556209943780,"c1":null,"sum":{"pas2":30289,"tSah":3801,"sah":159738,"janggal":10,"error":5,"cakupan":973,"pas1":129770,"jum":132425,"pending":76}},"43360":{"c1":null,"sum":{"pas1":210567,"pdi":319,"han":0,"dem":12,"pkb":403,"gol":177,"ber":5,"pbb":0,"pkp":1,"gar":0,"pJum":489,"per":11,"pTSah":35,"error":10,"cakupan":1639,"pending":20,"psi":5,"ger":76,"ppp":48,"nas":11,"tSah":6121,"janggal":10,"jum":212212,"pSah":289,"pas2":34694,"sej":3,"sah":244780,"pan":60},"ts":1556203460634},"43630":{"ts":1556210629679,"c1":null,"sum":{"pdi":40,"han":0,"psi":1,"dem":20,"ger":6,"ppp":8,"nas":4,"tSah":6578,"janggal":6,"jum":175886,"pkb":114,"gol":17,"pas2":34104,"pkp":0,"gar":0,"pan":12,"sah":201440,"pJum":203,"per":1,"error":1,"cakupan":1155,"pas1":167534,"pending":0}},"43993":{"c1":null,"sum":{"janggal":6,"jum":64380,"pSah":223,"pas2":38673,"sej":8,"sah":148786,"pan":7,"pas1":110113,"dem":20,"han":1,"pdi":67,"pkb":40,"gol":31,"ber":7,"pkp":2,"gar":0,"pJum":450,"per":17,"pTSah":164,"error":1,"cakupan":852,"pending":50,"psi":2,"ger":23,"ppp":57,"nas":11,"tSah":3236},"ts":1556209188961},"44417":{"ts":1556210387113,"c1":null,"sum":{"pkb":33,"gol":62,"ber":13,"pbb":0,"pkp":1,"gar":4,"per":6,"pTSah":20,"error":8,"cakupan":984,"pending":0,"psi":5,"ger":25,"ppp":9,"nas":21,"tSah":6232,"janggal":23,"jum":138838,"pSah":175,"pas2":79737,"sej":35,"sah":190345,"pan":1,"pas1":110597,"han":1,"dem":7,"pdi":55}},"44643":{"c1":null,"sum":{"pending":19,"pas2":79194,"tSah":5332,"sah":229137,"janggal":14,"error":8,"cakupan":1295,"pas1":149943,"jum":31707},"ts":1556217839009},"44923":{"sum":{"sah":111168,"pan":2,"pas1":82726,"pdi":78,"han":1,"dem":4,"pkb":14,"gol":6,"ber":1,"pbb":0,"pkp":0,"gar":0,"pJum":148,"per":7,"pTSah":14,"error":11,"cakupan":605,"pending":14,"psi":1,"ger":6,"ppp":10,"nas":4,"tSah":2037,"janggal":9,"jum":23353,"pSah":134,"pas2":28442,"sej":0},"ts":1556210888309,"c1":null},"45165":{"c1":null,"sum":{"tSah":1485,"janggal":2,"jum":9615,"pkb":33,"gol":10,"pas2":23907,"pbb":2,"pkp":0,"sah":39054,"error":1,"cakupan":233,"pas1":15178,"pending":0,"dem":1,"pdi":41,"han":0,"ger":12},"ts":1556196727620},"45407":{"c1":null,"sum":{"janggal":16,"error":20,"cakupan":1227,"pas1":99417,"jum":19954,"pending":11,"pas2":97682,"tSah":9151,"sah":197099},"ts":1556213622763},"45561":{"ts":1556181091023,"c1":null,"sum":{"pending":20,"pas2":17045,"tSah":1587,"sah":41649,"janggal":3,"error":6,"cakupan":221,"pas1":24846,"jum":13345}},"45916":{"ts":1556217455377,"c1":null,"sum":{"ber":53,"pbb":0,"pkp":1,"gar":2,"pJum":486,"per":5,"pTSah":137,"error":16,"cakupan":866,"pending":0,"psi":0,"ger":16,"ppp":14,"nas":25,"tSah":8553,"janggal":22,"jum":109039,"pSah":732,"pas2":75902,"sej":12,"sah":188246,"pan":7,"pas1":112341,"pdi":115,"han":48,"dem":20,"pkb":29,"gol":37}},"46306":{"ts":1556184827993,"c1":null,"sum":{"pkb":32,"gol":12,"ber":1,"pbb":0,"pkp":0,"gar":2,"pJum":2704,"per":16,"pTSah":16,"error":23,"cakupan":816,"pending":59,"psi":100,"ger":46,"ppp":1,"nas":11,"tSah":3722,"janggal":21,"jum":53902,"pSah":571,"pas2":47825,"sej":57,"sah":156381,"pan":10,"pas1":108556,"pdi":215,"han":0,"dem":18}},"46678":{"ts":1556169958504,"c1":null,"sum":{"tSah":9027,"sah":191521,"pJum":235,"janggal":26,"error":24,"cakupan":940,"pas1":146600,"jum":152848,"pending":25,"pas2":44921}},"47001":{"c1":null,"sum":{"dem":4,"pdi":14,"han":4,"pkb":80,"gol":8,"ber":5,"pbb":0,"pkp":0,"gar":0,"pJum":208,"per":2,"error":0,"cakupan":387,"pending":0,"ger":4,"nas":10,"tSah":2817,"janggal":6,"jum":28514,"pas2":16024,"sej":17,"pan":3,"sah":70162,"pas1":54135},"ts":1556171506312},"47329":{"sum":{"tSah":3027,"janggal":4,"jum":66682,"pkb":44,"gol":77,"ber":5,"pas2":20124,"sej":16,"gar":0,"sah":95272,"pJum":436,"error":0,"cakupan":588,"pas1":75148,"pending":64,"pdi":76,"ger":36,"nas":7},"ts":1556196969072,"c1":null},"47634":{"c1":null,"sum":{"pending":0,"pas2":7413,"tSah":1026,"sah":27818,"janggal":1,"error":2,"cakupan":162,"pas1":20405,"jum":15705},"ts":1556197370103},"47856":{"ts":1556186954838,"c1":null,"sum":{"pkp":1,"gar":0,"pJum":184,"per":2,"pTSah":55,"error":19,"cakupan":431,"pending":0,"psi":0,"ger":61,"ppp":2,"nas":6,"tSah":2696,"janggal":11,"jum":48345,"pSah":353,"pas2":28846,"sej":33,"sah":81416,"pas1":52570,"han":0,"dem":24,"pdi":8,"pkb":22,"gol":1,"ber":2,"pbb":1}},"48110":{"ts":1556207202442,"c1":null,"sum":{"tSah":3799,"janggal":7,"jum":34042,"pSah":156,"pas2":23025,"pJum":197,"sah":105745,"pTSah":23,"error":3,"pas1":82720,"cakupan":557,"pending":14}},"48347":{"sum":{"tSah":6072,"sah":182585,"janggal":27,"error":13,"cakupan":1005,"pas1":122513,"jum":107562,"pending":0,"pas2":60253},"ts":1556197139793,"c1":null},"48805":{"sum":{"tSah":6910,"janggal":19,"jum":85055,"pkb":32,"gol":33,"pas2":28138,"sah":108923,"error":12,"cakupan":632,"pas1":80787,"pending":25,"pdi":7,"ger":56},"ts":1556186064626,"c1":null},"49154":{"c1":null,"sum":{"janggal":6,"jum":61001,"pkb":80,"ber":1,"pas2":39018,"sej":1,"pkp":0,"gar":0,"pan":2,"sah":106992,"pJum":194,"per":1,"error":14,"cakupan":609,"pas1":67974,"pending":20,"dem":9,"ger":4,"ppp":1,"nas":2,"tSah":3948},"ts":1556180161489},"49656":{"c1":null,"sum":{"pSah":408,"pas2":62167,"pJum":221,"sah":187423,"pTSah":308,"error":17,"pas1":125256,"cakupan":906,"pending":15,"tSah":7711,"janggal":20,"jum":137465},"ts":1556172302422},"50031":{"ts":1556196603805,"c1":null,"sum":{"janggal":5,"error":8,"cakupan":402,"pas1":35169,"jum":16276,"pending":5,"pas2":41604,"tSah":2525,"sah":76773}},"50331":{"sum":{"tSah":2513,"sah":74985,"pTSah":0,"janggal":25,"error":17,"cakupan":373,"pas1":15707,"jum":21664,"pSah":184,"pending":4,"pas2":59436},"ts":1556196748052,"c1":null},"50532":{"sum":{"pSah":174,"pas2":109682,"sej":22,"sah":133318,"pan":125,"pas1":23646,"pdi":22,"han":15,"dem":53,"pkb":59,"gol":11,"ber":1,"pbb":35,"pkp":0,"gar":0,"pJum":532,"per":10,"pTSah":87,"error":20,"cakupan":929,"pending":309,"psi":1,"ger":12,"ppp":50,"nas":6,"tSah":2747,"janggal":26,"jum":49136},"ts":1556196487204,"c1":null},"50735":{"c1":null,"sum":{"janggal":6,"jum":12309,"pSah":164,"pas2":33737,"sej":3,"sah":49497,"pan":4,"pas1":15766,"han":6,"dem":6,"pdi":6,"pkb":21,"gol":3,"ber":2,"pbb":33,"pkp":0,"per":1,"pTSah":18,"error":9,"cakupan":308,"pending":9,"psi":0,"ger":34,"ppp":65,"nas":0,"tSah":2264},"ts":1556217133572},"51095":{"c1":null,"sum":{"nas":38,"tSah":2342,"janggal":22,"jum":93481,"pSah":433,"ber":6,"pas2":23559,"sej":9,"pbb":0,"pkp":0,"gar":1,"pan":13,"sah":109634,"per":7,"pTSah":109,"error":10,"cakupan":594,"pas1":86075,"pending":0,"han":0,"psi":4,"dem":0,"ppp":18},"ts":1556179291475},"51145":{"ts":1556199694433,"c1":null,"sum":{"pas2":7663,"tSah":681,"sah":30723,"janggal":2,"error":6,"cakupan":164,"pas1":23060,"jum":10564,"pending":1}},"51170":{"ts":1556197452541,"c1":null,"sum":{"pending":58,"pas2":44444,"tSah":2380,"sah":127247,"pTSah":23,"janggal":19,"error":17,"cakupan":652,"pas1":82903,"jum":54185,"pSah":215}},"51233":{"ts":1556172669243,"c1":null,"sum":{"pdi":52,"ger":18,"tSah":330,"janggal":1,"jum":2582,"pkb":67,"gol":32,"pas2":5799,"sah":13138,"error":2,"cakupan":132,"pas1":7339,"pending":39}},"51268":{"sum":{"tSah":1745,"sah":50161,"janggal":9,"error":7,"cakupan":256,"pas1":28164,"jum":15369,"pending":4,"pas2":21997},"ts":1556197266190,"c1":null},"51306":{"ts":1556212825620,"c1":null,"sum":{"tSah":681,"sah":27489,"janggal":1,"error":1,"cakupan":151,"pas1":19207,"jum":21461,"pending":9,"pas2":8282}},"51327":{"sum":{"tSah":1081,"janggal":8,"jum":38662,"pSah":355,"pas2":15434,"sej":30,"sah":54489,"pan":8,"pas1":39055,"pdi":42,"han":0,"dem":46,"pkb":21,"gol":6,"ber":3,"pbb":1,"pkp":0,"gar":0,"pJum":205,"per":6,"pTSah":33,"error":1,"cakupan":295,"pending":24,"psi":32,"ger":18,"ppp":0,"nas":49},"ts":1556223809484,"c1":null},"51358":{"ts":1556217213197,"c1":null,"sum":{"pkb":55,"gol":66,"ber":6,"pbb":6,"pkp":2,"gar":3,"pJum":213,"per":10,"error":28,"cakupan":1468,"pending":0,"psi":179,"ger":58,"ppp":0,"nas":87,"tSah":5160,"janggal":33,"jum":37385,"pas2":86117,"sej":10,"sah":288707,"pan":55,"pas1":202748,"han":1,"dem":29,"pdi":367}},"51550":{"sum":{"janggal":20,"jum":49177,"pkb":7,"pSah":133,"gol":5,"pas2":27633,"pbb":2,"pkp":2,"pan":16,"sah":101683,"per":11,"pTSah":26,"error":28,"cakupan":571,"pas1":74050,"pending":10,"han":1,"pdi":72,"psi":29,"dem":20,"ger":19,"ppp":0,"tSah":2724},"ts":1556188485040,"c1":null}},"parentIds":[0],"name":"JAWA TIMUR","parentNames":["IDN"],"id":42385,"children":[[42386,"PACITAN",1973,233201,237860],[42570,"PONOROGO",2937,371415,380921],[42897,"TRENGGALEK",2513,290984,290765],[43069,"TULUNGAGUNG",3768,423938,428632],[43360,"BLITAR",4753,472975,470865],[43630,"KEDIRI",5514,615568,610814],[43993,"MALANG",8409,996251,1000606],[44417,"LUMAJANG",3283,407462,427591],[44643,"JEMBER",7670,919712,943766],[44923,"BANYUWANGI",5120,653269,664312],[45165,"BONDOWOSO",2997,288052,310965],[45407,"SITUBONDO",2434,237254,255915],[45561,"PROBOLINGGO",3507,428994,455642],[45916,"PASURUAN",4377,581204,597904],[46306,"SIDOARJO",5600,689536,708034],[46678,"MOJOKERTO",3225,413654,417518],[47001,"JOMBANG",4299,500350,501467],[47329,"NGANJUK",3658,428891,430587],[47634,"MADIUN",2565,278884,293175],[47856,"MAGETAN",2207,257140,275537],[48110,"NGAWI",2768,346505,358587],[48347,"BOJONEGORO",4572,516783,523602],[48805,"TUBAN",3918,463671,476094],[49154,"LAMONGAN",4502,521851,534654],[49656,"GRESIK",3655,461212,465833],[50031,"BANGKALAN",3825,419684,446374],[50331,"SAMPANG",3693,404400,416541],[50532,"PAMEKASAN",3136,341906,364713],[50735,"SUMENEP",4319,410522,462242],[51095,"KOTA KEDIRI",971,99072,102778],[51145,"KOTA BLITAR",479,55462,58082],[51170,"KOTA MALANG",2365,305364,317821],[51233,"KOTA PROBOLINGGO",606,81719,86115],[51268,"KOTA PASURUAN",625,72326,75174],[51306,"KOTA MOJOKERTO",433,47854,50320],[51327,"KOTA MADIUN",605,70346,77195],[51358,"KOTA SURABAYA",8146,1041522,1090234],[51550,"KOTA BATU",757,77125,77701]]}