{"parentNames":["IDN"],"id":58285,"depth":1,"data":{"58286":{"sum":{"pkb":27,"gol":16,"ber":2,"pbb":37,"pkp":0,"gar":0,"pJum":584,"per":30,"pTSah":50,"error":3,"cakupan":202,"pending":0,"psi":0,"ger":12,"ppp":9,"nas":10,"tSah":1032,"janggal":6,"jum":24303,"pSah":300,"pas2":19803,"sej":36,"sah":36149,"pan":23,"pas1":16346,"pdi":32,"han":22,"dem":9},"ts":1556089731590,"c1":null},"58490":{"c1":null,"sum":{"gar":0,"sah":23058,"pTSah":106,"error":3,"cakupan":124,"pas1":5583,"pending":0,"nas":7,"tSah":548,"janggal":3,"jum":8785,"pkb":42,"pSah":122,"ber":3,"pas2":17475,"sej":18},"ts":1556031024657},"58567":{"sum":{"han":7,"dem":15,"pdi":25,"pkb":12,"gol":9,"ber":11,"pbb":1,"pkp":0,"gar":0,"per":6,"pTSah":22,"error":10,"cakupan":125,"pending":0,"psi":1,"ger":16,"ppp":4,"nas":3,"tSah":265,"janggal":5,"jum":6520,"pSah":155,"pas2":7652,"sej":11,"sah":20435,"pan":34,"pas1":12783},"ts":1556009983719,"c1":null},"58749":{"ts":1556089814892,"c1":null,"sum":{"pending":0,"pas2":15931,"tSah":503,"sah":25148,"pJum":203,"janggal":4,"error":4,"cakupan":124,"pas1":9217,"jum":5867}},"59018":{"c1":null,"sum":{"sah":27817,"error":14,"cakupan":144,"pas1":16853,"pending":0,"dem":0,"han":82,"tSah":389,"janggal":12,"jum":12543,"pas2":10964,"pbb":0,"pkp":0},"ts":1556063107592},"59320":{"ts":1555999881452,"c1":null,"sum":{"janggal":0,"error":1,"cakupan":48,"pas1":3857,"jum":2598,"pending":0,"pas2":2820,"tSah":124,"sah":6677}},"59557":{"c1":null,"sum":{"tSah":552,"sah":29469,"janggal":15,"error":6,"cakupan":185,"pas1":22580,"jum":22376,"pending":0,"pas2":6889},"ts":1556035243945},"59699":{"c1":null,"sum":{"tSah":354,"janggal":1,"jum":8590,"pkb":10,"gol":5,"ber":0,"pas2":4498,"sej":16,"gar":0,"sah":14330,"pJum":415,"error":5,"cakupan":114,"pas1":9832,"pending":34,"pdi":67,"ger":5,"nas":6},"ts":1556092323205},"59869":{"c1":null,"sum":{"tSah":311,"sah":26812,"janggal":3,"error":2,"cakupan":136,"pas1":15906,"jum":11766,"pending":0,"pas2":10906},"ts":1556063779621},"59953":{"ts":1555999800255,"c1":null,"sum":{"tSah":172,"sah":11575,"janggal":6,"error":4,"cakupan":51,"pas1":5914,"jum":7584,"pending":0,"pas2":5661}},"60134":{"c1":null,"sum":{"tSah":428,"janggal":1,"jum":5942,"pas2":5842,"pJum":235,"sah":9979,"pan":3,"per":23,"cakupan":57,"pas1":4137,"pending":0,"psi":1,"ppp":35},"ts":1556002599650},"60183":{"sum":{"pkb":35,"gol":22,"ber":2,"pbb":1,"pkp":0,"gar":0,"pJum":430,"per":15,"pTSah":45,"error":38,"cakupan":948,"pending":1,"psi":25,"ger":38,"ppp":17,"nas":23,"tSah":1826,"janggal":58,"jum":55747,"pSah":347,"pas2":109092,"sej":69,"sah":173419,"pan":11,"pas1":64191,"pdi":196,"han":2,"dem":7},"ts":1556100333755,"c1":null},"60223":{"c1":null,"sum":{"janggal":9,"error":7,"cakupan":111,"pas1":9033,"jum":6083,"pending":0,"pas2":10460,"tSah":337,"sah":19493},"ts":1556092425107},"60255":{"c1":null,"sum":{"pending":0,"pdi":33,"han":0,"dem":12,"ger":23,"ppp":2,"nas":19,"tSah":1566,"janggal":21,"jum":43236,"pkb":15,"pSah":129,"gol":94,"ber":8,"pas2":48381,"gar":0,"pan":8,"sah":72746,"pJum":134,"pTSah":5,"error":16,"cakupan":392,"pas1":24365},"ts":1556038230382}},"parentIds":[0],"name":"KALIMANTAN BARAT","children":[[58286,"SAMBAS",1701,217630,211701],[58490,"MEMPAWAH",827,95445,93374],[58567,"SANGGAU",1642,171392,159400],[58749,"KETAPANG",1567,193146,180882],[59018,"SINTANG",1417,151390,143996],[59320,"KAPUAS HULU",933,91159,87776],[59557,"BENGKAYANG",792,92924,86082],[59699,"LANDAK",1364,144041,130900],[59869,"SEKADAU",676,78272,74014],[59953,"MELAWI",707,82267,78904],[60134,"KAYONG UTARA",331,41346,39424],[60183,"KOTA PONTIANAK",2003,226757,232132],[60223,"KOTA SINGKAWANG",673,80921,79832],[60255,"KUBU RAYA",1867,213194,208858]]}