{"id":64111,"name":"KALIMANTAN TIMUR","depth":1,"parentIds":[0],"parentNames":["IDN"],"children":[[64112,"PASER",793,96105,89725],[64248,"KUTAI KARTANEGARA",2124,252802,232761],[64496,"BERAU",690,80416,69812],[65069,"KUTAI BARAT",509,60469,54403],[65315,"KUTAI TIMUR",971,123053,104270],[65469,"PENAJAM PASER UTARA",515,63787,59080],[65528,"KOTA BALIKPAPAN",2051,233830,230284],[65567,"KOTA SAMARINDA",2549,299533,286823],[65656,"KOTA BONTANG",516,62556,57827],[928073,"MAHAKAM ULU",106,12519,10686]],"data":{"64112":{"sum":{"pending":88,"janggal":8,"cakupan":346,"pas2":28380,"tSah":976,"sah":47607,"pas1":19227,"jum":30386,"error":4,"pTSah":85,"pSah":123,"pJum":208},"ts":1555997108678,"c1":null},"64248":{"sum":{"janggal":8,"cakupan":261,"pending":104,"pas2":19264,"tSah":604,"sah":32670,"pas1":13406,"jum":3038,"error":9},"ts":1555997058694,"c1":null},"64496":{"sum":{"pending":70,"janggal":4,"cakupan":127,"pas2":5472,"tSah":189,"sah":11812,"pas1":6340,"jum":626,"error":1},"ts":1556006070949,"c1":null},"65069":{"sum":{"janggal":3,"cakupan":43,"pending":0,"pas2":1411,"tSah":150,"sah":7120,"pas1":5709,"jum":4206,"error":1},"ts":1555975799459,"c1":null},"65315":{"sum":{"janggal":6,"cakupan":224,"pending":12,"pas2":13887,"tSah":626,"sah":40071,"pas1":26177,"jum":19262,"error":4},"ts":1556010095632,"c1":null},"65469":{"sum":{"janggal":1,"cakupan":130,"pending":38,"tSah":435,"sah":18533,"pas1":10219,"pas2":8314,"jum":11372,"error":1,"pkb":5},"ts":1555976602560,"c1":null},"65528":{"sum":{"janggal":18,"cakupan":404,"pending":92,"pas1":31639,"pas2":28791,"tSah":892,"sah":60430,"error":21,"jum":6785,"han":0,"psi":0,"ber":0,"pkb":0},"ts":1555996621061,"c1":null},"65567":{"sum":{"janggal":4,"cakupan":532,"pending":312,"pas2":21993,"tSah":662,"sah":39279,"pas1":17286,"jum":3411,"pkb":2,"psi":0,"ppp":2,"pan":4,"per":5,"error":2},"ts":1556008450008,"c1":null},"65656":{"sum":{"pending":47,"janggal":2,"cakupan":100,"tSah":94,"sah":9217,"pas1":4785,"pas2":4432,"jum":2453,"error":2},"ts":1556011700417,"c1":null},"928073":{"sum":{"pending":0,"janggal":0,"cakupan":8,"jum":1129,"pas2":185,"tSah":19,"sah":1325,"pas1":1140},"ts":1555947215496,"c1":null}}}