{"id":64111,"name":"KALIMANTAN TIMUR","depth":1,"parentIds":[0],"parentNames":["IDN"],"children":[[64112,"PASER",803,96105,89725],[64248,"KUTAI KARTANEGARA",2144,252802,232761],[64496,"BERAU",705,80416,69812],[65069,"KUTAI BARAT",952,60469,54403],[65315,"KUTAI TIMUR",971,123053,104270],[65469,"PENAJAM PASER UTARA",515,63787,59080],[65528,"KOTA BALIKPAPAN",2055,233830,230284],[65567,"KOTA SAMARINDA",2558,299533,286823],[65656,"KOTA BONTANG",516,62556,57827],[928073,"MAHAKAM ULU",115,12519,10686]],"data":{"64112":{"sum":{"pending":0,"janggal":52,"cakupan":748,"pas2":73574,"tSah":3565,"sah":136760,"pas1":63597,"jum":138197,"error":0,"pTSah":85,"pSah":123,"pJum":208,"laporKpu":0},"ts":1557152069921,"c1":null},"64248":{"sum":{"janggal":82,"cakupan":1629,"pending":37,"pas2":125832,"tSah":7413,"sah":287978,"pas1":163170,"jum":282385,"error":1,"laporKpu":0},"ts":1557153307487,"c1":null},"64496":{"sum":{"pending":62,"janggal":44,"cakupan":457,"pas2":28651,"tSah":1445,"sah":69631,"pas1":41362,"jum":60951,"error":0,"laporKpu":0},"ts":1556994677098,"c1":null},"65069":{"sum":{"janggal":15,"cakupan":295,"pending":0,"pas2":9395,"tSah":996,"sah":45417,"pas1":36124,"jum":45078,"error":0},"ts":1556995128325,"c1":null},"65315":{"sum":{"janggal":70,"cakupan":585,"pending":0,"pas2":38827,"tSah":1808,"sah":108272,"pas1":69697,"jum":101333,"error":0,"pdi":17,"ger":12,"pkb":3,"gol":12,"ber":26,"sej":32,"gar":0,"nas":65,"pan":18,"per":23,"psi":1,"ppp":109},"ts":1556995686922,"c1":null},"65469":{"sum":{"janggal":7,"cakupan":144,"pending":0,"tSah":701,"sah":28373,"pas1":15126,"pas2":13267,"jum":21482,"error":0,"pkb":5},"ts":1556995870894,"c1":null},"65528":{"sum":{"janggal":114,"cakupan":1732,"pending":0,"pas1":163126,"pas2":136090,"tSah":6906,"sah":297377,"error":0,"jum":292447,"han":0,"psi":0,"ber":0,"pkb":0,"laporKpu":0},"ts":1557053355066,"c1":null},"65567":{"sum":{"janggal":119,"cakupan":1497,"pending":0,"pas2":128399,"tSah":4972,"sah":241371,"pas1":113342,"jum":193177,"pkb":2,"psi":0,"ppp":2,"pan":4,"per":5,"error":0,"pTSah":28,"pSah":234,"pJum":194,"gol":190,"pdi":23,"ger":20,"laporKpu":0},"ts":1557063547359,"c1":null},"65656":{"sum":{"pending":0,"janggal":29,"cakupan":391,"tSah":1355,"sah":72642,"pas1":40455,"pas2":32531,"jum":66024,"error":0,"nas":36,"ber":0,"sej":31,"gar":0,"psi":4,"ppp":3,"pan":5,"per":3,"pkb":9,"gol":31,"pdi":17,"ger":2},"ts":1556996712819,"c1":null},"928073":{"sum":{"pending":0,"janggal":4,"cakupan":37,"jum":6078,"pas2":930,"tSah":313,"sah":5645,"pas1":4818,"error":0},"ts":1556995949541,"c1":null}}}