{"data":{"67394":{"c1":null,"sum":{"pending":0,"pas2":47576,"tSah":1762,"sah":112311,"laporKpu":0,"janggal":32,"error":0,"cakupan":684,"pas1":65277,"jum":111971},"ts":1557439709934},"67558":{"sum":{"per":3,"error":0,"cakupan":288,"pas1":25111,"pending":22,"han":12,"psi":12,"dem":6,"ppp":3,"tSah":489,"laporKpu":0,"janggal":13,"jum":27189,"pas2":18073,"sej":5,"pbb":0,"pkp":0,"pan":15,"sah":43184,"pJum":220},"ts":1557452407771,"c1":null},"67866":{"c1":null,"sum":{"tSah":596,"sah":75227,"laporKpu":4,"janggal":19,"error":0,"cakupan":469,"pas1":51313,"jum":75216,"pkb":34,"pending":33,"pas2":23964},"ts":1557335290985},"68041":{"sum":{"tSah":2585,"sah":157067,"laporKpu":12,"janggal":43,"error":0,"cakupan":851,"pas1":95297,"jum":160752,"pending":40,"pas2":62763},"ts":1557396575570,"c1":null},"68206":{"ts":1557239160527,"c1":null,"sum":{"pending":2,"pas2":57246,"tSah":2022,"sah":121224,"laporKpu":19,"janggal":40,"error":0,"cakupan":726,"pas1":64425,"jum":123569}},"68309":{"c1":null,"sum":{"janggal":33,"error":0,"cakupan":420,"pas1":39562,"jum":80674,"pending":2,"pas2":40762,"tSah":1238,"sah":80179,"laporKpu":6},"ts":1557230077753},"68428":{"sum":{"tSah":984,"sah":77828,"laporKpu":1,"janggal":39,"error":0,"cakupan":405,"pas1":31264,"jum":78950,"pending":1,"pas2":46646},"ts":1557229924122,"c1":null},"68681":{"ts":1557236168476,"c1":null,"sum":{"pas2":30732,"tSah":770,"sah":69425,"laporKpu":1,"janggal":17,"error":0,"cakupan":397,"pas1":38739,"jum":71373,"pending":1}},"68887":{"c1":null,"sum":{"janggal":24,"error":0,"cakupan":744,"pas1":74739,"jum":108352,"pending":128,"pas2":37004,"tSah":1399,"sah":111582,"laporKpu":2},"ts":1557454243799},"69089":{"ts":1557236330647,"c1":null,"sum":{"tSah":1130,"laporKpu":0,"janggal":22,"jum":84520,"pkb":22,"gol":0,"ber":3,"pas2":43288,"sej":9,"gar":0,"sah":82311,"error":0,"cakupan":470,"pas1":39271,"pending":1,"pdi":4,"ger":33,"nas":28}},"69220":{"c1":null,"sum":{"tSah":731,"sah":74463,"laporKpu":0,"janggal":39,"error":0,"cakupan":673,"pas1":28252,"jum":56146,"pending":286,"pas2":46225},"ts":1557453359091},"928074":{"ts":1557221986726,"c1":null,"sum":{"pas2":17682,"tSah":362,"sah":34297,"laporKpu":0,"janggal":11,"cakupan":190,"pas1":16619,"jum":34863,"pending":7}},"928075":{"ts":1557229793862,"c1":null,"sum":{"tSah":494,"sah":42332,"laporKpu":0,"janggal":7,"cakupan":242,"pas1":31678,"jum":43337,"pending":4,"pas2":10654}}},"parentIds":[0],"name":"SULAWESI TENGAH","parentNames":["IDN"],"id":67393,"depth":1,"children":[[67394,"SIGI",853,83702,80403],[67558,"BANGGAI",1170,129309,126651],[67866,"POSO",766,75021,72215],[68041,"DONGGALA",869,105169,99879],[68206,"TOLITOLI",746,76348,73092],[68309,"BUOL",430,49715,47274],[68428,"MOROWALI",414,50542,45515],[68681,"BANGGAI KEPULAUAN",397,39581,38866],[68887,"PARIGI MOUTONG",1339,155379,148562],[69089,"TOJO UNA-UNA",524,58858,55800],[69220,"KOTA PALU",1076,105463,108494],[928074,"BANGGAI LAUT",212,22833,22617],[928075,"MOROWALI UTARA",395,42253,39269]]}